haralyzer_3/__init__.py
haralyzer_3/assets.py
haralyzer_3/errors.py
haralyzer_3/http.py
haralyzer_3/mixins.py
haralyzer_3/multihar.py
haralyzer_3-1.9.0.dist-info/LICENSE.txt
haralyzer_3-1.9.0.dist-info/METADATA
haralyzer_3-1.9.0.dist-info/WHEEL
haralyzer_3-1.9.0.dist-info/top_level.txt
haralyzer_3-1.9.0.dist-info/RECORD
