Metadata-Version: 2.1
Name: haralyzer-3
Version: 1.9.0
Summary: A Python 3 fork of haralyzer which is a framework for getting useful stuff out of HAR files
Home-page: https://github.com/Cyb3r-Jak3/haralyzer_3
Author: Cyb3r Jak3
Author-email: jake@jwhite.network
License: MIT
Download-URL: https://github.com/Cyb3r-Jak3/haralyzer_3/releases/latest
Project-URL: Changelog, https://github.com/Cyb3r-Jak3/haralyzer_3/blob/master/HISTORY.rst
Project-URL: Docs, https://haralyzer-3.readthedocs.io/en/latest/
Project-URL: Say Thanks!, https://saythanks.io/to/jake%40jwhite.network
Keywords: har
Platform: UNKNOWN
Classifier: Development Status :: 5 - Production/Stable
Classifier: Intended Audience :: Developers
Classifier: License :: OSI Approved :: MIT License
Classifier: Natural Language :: English
Classifier: Programming Language :: Python :: 3 :: Only
Classifier: Programming Language :: Python :: 3
Classifier: Programming Language :: Python :: 3.6
Classifier: Programming Language :: Python :: 3.7
Classifier: Programming Language :: Python :: 3.8
Classifier: Programming Language :: Python :: 3.9
Classifier: Programming Language :: Python :: Implementation :: CPython
Requires-Dist: cached-property
Requires-Dist: python-dateutil
Requires-Dist: six (>=1.13.0)
Provides-Extra: request
Requires-Dist: requests (==2.25.0) ; extra == 'request'
